pylhc/__init__.py
pylhc/bpm_calibration.py
pylhc/bsrt_analysis.py
pylhc/bsrt_logger.py
pylhc/forced_da_analysis.py
pylhc/kickgroups.py
pylhc/lsa_to_madx.py
pylhc/machine_settings_info.py
pylhc/calibration/__init__.py
pylhc/calibration/beta.py
pylhc/calibration/dispersion.py
pylhc/constants/__init__.py
pylhc/constants/calibration.py
pylhc/constants/forced_da_analysis.py
pylhc/constants/general.py
pylhc/constants/kickgroups.py
pylhc/constants/machine_settings_info.py
pylhc/data_extract/__init__.py
pylhc/data_extract/lsa.py
pylhc/data_extract/timber.py
pylhc-0.8.2.dist-info/METADATA
pylhc-0.8.2.dist-info/WHEEL
pylhc-0.8.2.dist-info/licenses/LICENSE
pylhc-0.8.2.dist-info/RECORD
