Metadata-Version: 2.4
Name: pylhc
Version: 0.8.2
Summary: An accelerator physics script collection for the OMC team at CERN.
Project-URL: homepage, https://github.com/pylhc/PyLHC
Project-URL: repository, https://github.com/pylhc/PyLHC
Project-URL: documentation, https://pylhc.github.io/PyLHC/
Project-URL: changelog, https://github.com/pylhc/PyLHC/blob/master/CHANGELOG.md
Author-email: OMC Team <pylhc@github.com>
License-Expression: MIT
License-File: LICENSE
Classifier: Intended Audience :: Science/Research
Classifier: License :: OSI Approved :: MIT License
Classifier: Natural Language :: English
Classifier: Operating System :: OS Independent
Classifier: Programming Language :: Python :: 3 :: Only
Classifier: Programming Language :: Python :: 3.10
Classifier: Programming Language :: Python :: 3.11
Classifier: Programming Language :: Python :: 3.12
Classifier: Programming Language :: Python :: 3.13
Classifier: Programming Language :: Python :: 3.14
Classifier: Programming Language :: Python :: Implementation :: CPython
Classifier: Topic :: Scientific/Engineering
Classifier: Topic :: Software Development :: Libraries :: Python Modules
Classifier: Typing :: Typed
Requires-Python: >=3.10
Requires-Dist: generic-parser>=1.1
Requires-Dist: jpype1>=1.3
Requires-Dist: matplotlib>=3.8
Requires-Dist: numpy>=1.24
Requires-Dist: omc3>=0.15
Requires-Dist: pandas>=2.1
Requires-Dist: parse>=1.15
Requires-Dist: scipy>=1.10
Requires-Dist: tfs-pandas>=3.8
Provides-Extra: all
Requires-Dist: omc3[cern]>=0.15; extra == 'all'
Requires-Dist: pjlsa>=0.2; extra == 'all'
Requires-Dist: pyjapc; extra == 'all'
Requires-Dist: pytest-cov>=2.9; extra == 'all'
Requires-Dist: pytest-mpl>=0.15; extra == 'all'
Requires-Dist: pytest>=7.0; extra == 'all'
Requires-Dist: pytimber>=3.0; extra == 'all'
Requires-Dist: sphinx-rtd-theme>=2.0; extra == 'all'
Requires-Dist: sphinx>=7.0; extra == 'all'
Provides-Extra: cern
Requires-Dist: omc3[cern]>=0.15; extra == 'cern'
Requires-Dist: pjlsa>=0.2; extra == 'cern'
Requires-Dist: pyjapc; extra == 'cern'
Requires-Dist: pytimber>=3.0; extra == 'cern'
Provides-Extra: doc
Requires-Dist: sphinx-rtd-theme>=2.0; extra == 'doc'
Requires-Dist: sphinx>=7.0; extra == 'doc'
Provides-Extra: test
Requires-Dist: pytest-cov>=2.9; extra == 'test'
Requires-Dist: pytest-mpl>=0.15; extra == 'test'
Requires-Dist: pytest>=7.0; extra == 'test'
